[
  {
    "description": "Tree 1",
    "supplier": "@user3674",
    "company": "Company",
    "contact": "xyz@email.com",
    "location": "Berlin, Germany"
  },
  {
    "description": "Tree 1",
    "supplier": "@user3674",
    "company": "Company",
    "contact": "xyz@email.com",
    "location": "Berlin, Germany"
  },
  {
    "description": "Tree 1",
    "supplier": "@user3674",
    "company": "Company",
    "contact": "xyz@email.com",
    "location": "Berlin, Germany"
  },
  {
    "description": "Tree 1",
    "supplier": "@user3674",
    "company": "Company",
    "contact": "xyz@email.com",
    "location": "Berlin, Germany"
  },
  {
    "description": "Tree 1",
    "supplier": "@user3674",
    "company": "Company",
    "contact": "xyz@email.com",
    "location": "Berlin, Germany"
  },
  {
    "description": "Tree 1",
    "supplier": "@user3674",
    "company": "Company",
    "contact": "xyz@email.com",
    "location": "Berlin, Germany"
  }
]
